pre/verilog/recongnition/recognition.v
`timescale 1ns / 1ps
`define s0 0
`define s1 1
`define s2 2
`define s3 3

module recognition(
    input in,
    input clk,
    input reset,
    output reg out
    );
    reg [1:0] status=`s0;

    always@(posedge clk, reset) begin
        out<=0;
        if (reset) begin
            out<=0;
            status<=`s0;
        end
        else begin
            if(status==`s0) begin
                if(in) status<=`s1;
                else status<=`s0;
            end
            else if (status==`s1) begin
                if(in==0) status<=`s2;
                else status<=`s1;
            end
            else if (status==`s2) begin
                if(in) begin
                    out<=1;
                    status<=`s3;
                end
                else status<=`s0;
            end
            else if (status==`s3) begin
                if(in) status<=`s1;
                else status<=`s2;
            end
        end
    end

endmodule

CO/pre/verilog/recongnition/tb_recongnition.v
`include "recognition.v"
`timescale  1ns / 1ps    

module tb_recognition;   

reg   clk                                  = 0 ;
reg   reset                                = 0 ;
reg   in                                   = 0 ;
wire  out                                  ;

recognition  u_recognition (
    .clk                     ( clk     ),
    .reset                   ( reset   ),
    .in                      ( in      ),

    .out                     ( out     )
);

initial
begin
    $dumpfile("wave.vcd");
	$dumpvars;
    clk=0;
    reset=1;
    in = 0;
    #2 reset=0;
    #2 in=1;
    #2 in=0;
    #2 in=1;
    #2 in=0;
    #2 in=1;
    #10
    $finish;
end
always #1 clk=~clk;
endmodule

pre/verilog/recongnition/wave.vcd
$date
	Tue Sep 27 23:43:17 2022
$end
$version
	Icarus Verilog
$end
$timescale
	1ps
$end
$scope module tb_recognition $end
$var wire 1 ! out $end
$var reg 1 " clk $end
$var reg 1 # in $end
$var reg 1 $ reset $end
$scope module u_recognition $end
$var wire 1 " clk $end
$var wire 1 # in $end
$var wire 1 $ reset $end
$var reg 1 ! out $end
$var reg 2 % status [1:0] $end
$upscope $end
$upscope $end
$enddefinitions $end
#0
$dumpvars
b0 %
1$
0#
0"
0!
$end
#1000
1"
#2000
0"
0$
#3000
1"
#4000
0"
1#
#5000
b1 %
1"
#6000
0"
0#
#7000
b10 %
1"
#8000
0"
1#
#9000
b11 %
1!
1"
#10000
0"
0#
#11000
b10 %
0!
1"
#12000
0"
1#
#13000
b11 %
1!
1"
#14000
0"
#15000
b1 %
0!
1"
