pre/verilog/counter/counter.v
`timescale 1ns/1ps
module code (
    input Clk,
    input Reset,
    input Slt,
    input En,
    output reg [63:0] Output0,
    output reg [63:0] Output1
);
    initial begin
        Output0=0;
        Output1=0;
    end
    integer temp=0;
    always @ (posedge Clk) begin
        if(Reset) begin
            Output0<=0;
            Output1<=0;
            temp<=0;
        end else if(En) begin
            if(!Slt) Output0<=Output0+1;
            else begin
                temp=temp+1;
                if(temp==4) begin
                    Output1<=Output1+1;
                    temp<=0;
                end
            end
        end
        else ;
    end
endmodule

CO/pre/verilog/counter/tb_counter.v
`timescale 1ns/1ps
`include "counter.v"
module tb_counter;

// code Parameters
parameter PERIOD  = 10;
// code Inputs
reg   Clk                                  = 0 ;
reg   Reset                                = 0 ;
reg   Slt                                  = 0 ;
reg   En                                   = 0 ;

// code Outputs
wire  [63:0]  Output0                      ;
wire  [63:0]  Output1                      ;


initial
begin
    forever #(PERIOD/2)  Clk=~Clk;
end

code  u_code (
    .Clk                     ( Clk             ),
    .Reset                   ( Reset           ),
    .Slt                     ( Slt             ),
    .En                      ( En              ),

    .Output0                 ( Output0  [63:0] ),
    .Output1                 ( Output1  [63:0] )
);

initial
begin
    Reset=0;
    En=0;
    Slt=0;
    #20;
    Reset=0;
    En=1;   
    Slt=0; 
    #10;
    $display ("%d %d",Output0,Output1);
    Reset=0;
    En=1;   
    Slt=0; 
    #10;
    $display ("%d %d",Output0,Output1);
    Reset=0;
    En=1;   
    Slt=1; 
    #10;
    $display ("%d %d",Output0,Output1);
    Reset=0;
    En=1;   
    Slt=1; 
    #10;
    $display ("%d %d",Output0,Output1);
    Reset=0;
    En=1;   
    Slt=1; 
    #10;
    $display ("%d %d",Output0,Output1);
    Reset=0;
    En=1;   
    Slt=1; 
    #10;
    $display ("%d %d",Output0,Output1);
    Reset=0;
    En=1;   
    Slt=1; 
    #10;
    $display ("%d %d",Output0,Output1);
    Reset=1;
    En=1;   
    Slt=1; 
    #10;
    $display ("%d %d",Output0,Output1);
    Reset=0;
    En=1;   
    Slt=1; 
    #10;
    $display ("%d %d",Output0,Output1);
    Reset=0;
    En=1;   
    Slt=1; 
    #10;
    $display ("%d %d",Output0,Output1);
    Reset=0;
    En=1;   
    Slt=1; 
    #10;
    $display ("%d %d",Output0,Output1);
    Reset=0;
    En=1;   
    Slt=1; 
    #10;
    $display ("%d %d",Output0,Output1);
    #5;
    $finish;
end

    initial
  begin
      $dumpfile("tb_counter.vcd");        //生成的vcd文件名称
      $dumpvars(0, tb_counter);    //tb模块名称
  end 
endmodule

pre/verilog/counter/tb_counter.vcd
$date
	Tue Sep 27 17:16:40 2022
$end
$version
	Icarus Verilog
$end
$timescale
	1ps
$end
$scope module tb_counter $end
$var wire 64 ! Output1 [63:0] $end
$var wire 64 " Output0 [63:0] $end
$var reg 1 # Clk $end
$var reg 1 $ En $end
$var reg 1 % Reset $end
$var reg 1 & Slt $end
$scope module u_code $end
$var wire 1 # Clk $end
$var wire 1 $ En $end
$var wire 1 % Reset $end
$var wire 1 & Slt $end
$var reg 64 ' Output0 [63:0] $end
$var reg 64 ( Output1 [63:0] $end
$var integer 32 ) temp [31:0] $end
$upscope $end
$upscope $end
$enddefinitions $end
#0
$dumpvars
b0 )
b0 (
b0 '
0&
0%
0$
0#
b0 "
b0 !
$end
#5000
1#
#10000
0#
#15000
1#
#20000
0#
1$
#25000
b1 "
b1 '
1#
#30000
0#
#35000
b10 "
b10 '
1#
#40000
0#
1&
#45000
b1 )
1#
#50000
0#
#55000
b10 )
1#
#60000
0#
#65000
b11 )
1#
#70000
0#
#75000
b1 !
b1 (
b0 )
1#
#80000
0#
#85000
b1 )
1#
#90000
0#
1%
#95000
b0 )
b0 !
b0 (
b0 "
b0 '
1#
#100000
0#
0%
#105000
b1 )
1#
#110000
0#
#115000
b10 )
1#
#120000
0#
#125000
b11 )
1#
#130000
0#
#135000
b1 !
b1 (
b0 )
1#
#140000
0#
#145000
b1 )
1#
