CO/pre/verilog/trans_counting123/counting123.v
`define s0 2'b00
`define s1 2'b01
`define s2 2'b10
`define s3 2'b11


module counting(
    input [1:0] num,
    input clk,
    output ans
    
    );
reg [1:0] status=2'b00;
always@(posedge clk)
begin
    if(status==`s0) begin
        if(num==1) status<=`s1;
        else status<=`s0;
    end // if(status==`s0)
    else if(status==`s1) begin
        if(num==2) status<=`s2;
        else if(num==1) status<=`s1;
        else status<=`s0;
    end
    else if(status==`s2) begin
        if(num==3) status<=`s3;
        else if(num==2) status<=`s2;
        else if(num==1) status<=`s1;
        else status<=`s0;
    end
    else if(status==`s3) begin
        if(num==3) status<=`s3;
        else if(num==1) status<=`s1;
        else status<=`s0;
    end
    else status<=`s0;
end

    assign ans = (status == `s3) ? 1'b1 : 1'b0;
endmodule // counting

pre/verilog/trans_counting123/tb_counting.v
`timescale  1ns / 1ps
`include "counting123.v"
module tb_counting;

// counting Parameters
parameter PERIOD  = 10;

// counting Inputs
reg   [1:0]  num                           = 0 ;
reg   clk                                  = 0 ;
// counting Outputs
wire  ans                                  ;

initial
begin
    forever #(PERIOD/2)  clk=~clk;
end


counting  u_counting (
    .num                     ( num  [1:0] ),
    .clk                     ( clk        ),

    .ans                     ( ans        )
);

initial
begin
    num=0;
    clk=0;
    #20;
    num=1;
    @(negedge clk);
    $display("%d ",ans);

        num=1;
@(negedge clk);
    $display("%d ",ans);

    num=2;
@(negedge clk);
    $display("%d ",ans);
        num=3;
@(negedge clk);
    $display("%d ",ans);

    num=3;
@(negedge clk);
    $display("%d ",ans);

    num=1;
@(negedge clk);
    $display("%d ",ans);

    num=2;
@(negedge clk);
    $display("%d ",ans);

    num=1;
@(negedge clk);
    $display("%d ",ans);

        num=1;
@(negedge clk);
    $display("%d ",ans);

        num=1;
@(negedge clk);
    $display("%d ",ans);

        num=2;
@(negedge clk);
    $display("%d ",ans);

     num=2;
@(negedge clk);
    $display("%d ",ans);

 num=3;
@(negedge clk);
    $display("%d ",ans);

        num=3;
@(negedge clk);
    $display("%d ",ans);
    
        num=3;
@(negedge clk);
        $display("%d ",ans);

                num=1;
@(negedge clk);
        $display("%d ",ans);

    #20;
    $finish;
end
  initial
  begin            
      $dumpfile("tb_counting.vcd");        //生成的vcd文件名称
      $dumpvars(0, tb_counting);    //tb模块名称
  end 
endmodule

CO/pre/verilog/trans_counting123/tb_counting.vcd
$date
	Tue Sep 27 23:42:18 2022
$end
$version
	Icarus Verilog
$end
$timescale
	1ps
$end
$scope module tb_counting $end
$var wire 1 ! ans $end
$var reg 1 " clk $end
$var reg 2 # num [1:0] $end
$scope module u_counting $end
$var wire 1 " clk $end
$var wire 2 $ num [1:0] $end
$var wire 1 ! ans $end
$var reg 2 % status [1:0] $end
$upscope $end
$upscope $end
$enddefinitions $end
#0
$dumpvars
b0 %
b0 $
b0 #
0"
0!
$end
#5000
1"
#10000
0"
#15000
1"
#20000
0"
b1 #
b1 $
#25000
b1 %
1"
#30000
b10 #
b10 $
0"
#35000
b10 %
1"
#40000
b11 #
b11 $
0"
#45000
1!
b11 %
1"
#50000
0"
#55000
1"
#60000
b1 #
b1 $
0"
#65000
0!
b1 %
1"
#70000
b10 #
b10 $
0"
#75000
b10 %
1"
#80000
b1 #
b1 $
0"
#85000
b1 %
1"
#90000
0"
#95000
1"
#100000
0"
#105000
1"
#110000
b10 #
b10 $
0"
#115000
b10 %
1"
#120000
0"
#125000
1"
#130000
b11 #
b11 $
0"
#135000
1!
b11 %
1"
#140000
0"
#145000
1"
#150000
0"
#155000
1"
#160000
b1 #
b1 $
0"
#165000
0!
b1 %
1"
