pre/verilog/id_fsm/id_fsm.v
module id_fsm(
    input [7:0] char,
    input clk,
    output reg out
    );
    reg flag;

    initial begin
        out=0;
    end

    always@(posedge clk) begin
        if((char>="A" && char<="Z")||(char>=8'd65 && char<=8'd90)) begin
            flag<=1;
            out<=0;
        end
        else if((char>=8'd48 && char<=8'd57)) begin
            if(flag) out<=1;
            else out<=0;
        end
        else begin
            out<=0;
            flag<=0;
        end
    end

endmodule

CO/pre/verilog/id_fsm/tb_id_fsm.v
`timescale  1ns / 1ps
`include "id_fsm.v"
module tb_id_fsm;
// id_fsm Parameters
parameter PERIOD  = 10;

// id_fsm Inputs
reg   [7:0]  char                          = 0 ;
reg   clk                                  = 0 ;
// id_fsm Outputs
wire  out                                  ;

initial
begin
    forever #(PERIOD/2)  clk=~clk;
end


id_fsm  u_id_fsm (
    .char                    ( char  [7:0] ),
    .clk                     ( clk         ),

    .out                     ( out         )
);

initial
begin
    char=30;
    #20;
    $display("%d",out);
    char=88;
    #10;
    $display("%d",out);
        char=30;
    #10;
    $display("%d",out);
        char=30;
    #10;
    $display("%d",out);
        char=29;
    #10;
    $display("%d",out);
        char=89;
    #10;
    $display("%d",out);
    $finish;
end
    initial
    begin
        $dumpfile("tb_id_fsm.vcd");        //生成的vcd文件名称
        $dumpvars(0, tb_id_fsm);    //tb模块名称
    end 
endmodule

pre/verilog/id_fsm/tb_id_fsm.vcd
$date
	Tue Aug 23 20:42:25 2022
$end
$version
	Icarus Verilog
$end
$timescale
	1ps
$end
$scope module tb_id_fsm $end
$var wire 1 ! out $end
$var reg 8 " char [7:0] $end
$var reg 1 # clk $end
$scope module u_id_fsm $end
$var wire 8 $ char [7:0] $end
$var wire 1 # clk $end
$var reg 1 % flag $end
$var reg 1 ! out $end
$upscope $end
$upscope $end
$enddefinitions $end
#0
$dumpvars
x%
b11110 $
0#
b11110 "
0!
$end
#5000
1#
#10000
0#
#15000
1#
#20000
0#
b1011000 "
b1011000 $
#25000
1%
1#
#30000
0#
b11110 "
b11110 $
#35000
1!
1#
#40000
0#
#45000
1#
#50000
0#
b11101 "
b11101 $
#55000
0%
0!
1#
#60000
0#
b1011001 "
b1011001 $
#65000
1%
1#
